{"cameraMode":{"drawMode":0,"name":"Shaded","section":"Shading Mode"},"sceneLighting":true,"audioPlay":false,"sceneViewState":{"showFog":true,"showMaterialUpdate":false,"showSkybox":true,"showFlares":true,"showImageEffects":true,"showParticleSystems":true},"in2DMode":false,"pivot":{"x":13.343260765075684,"y":1.4530000686645508,"z":72.12999725341797},"rotation":{"x":0.12647265195846559,"y":-0.8735265731811523,"z":0.3318023979663849,"w":0.3329613208770752},"size":3.8978216648101808,"orthographic":false}